LICENSE
MANIFEST.in
README.rst
setup.py
PedalPi_Application.egg-info/PKG-INFO
PedalPi_Application.egg-info/SOURCES.txt
PedalPi_Application.egg-info/dependency_links.txt
PedalPi_Application.egg-info/requires.txt
PedalPi_Application.egg-info/top_level.txt
application/__init__.py
application/application.py
application/component/__init__.py
application/component/application_observer.py
application/component/component.py
application/component/components_observer.py
application/component/current_pedalboard_observer.py
application/controller/__init__.py
application/controller/component_data_controller.py
application/controller/controller.py
application/controller/current_controller.py
application/controller/device_controller.py
application/controller/plugins_controller.py
application/dao/__init__.py
application/dao/component_dao.py
application/dao/current_dao.py
application/dao/plugins_dao.py
application/data/__init__.py
application/data/banks/9f0cd4fa-8fc8-48a4-9513-056aba8fd841.json
application/data/banks/__init__.py
application/data/components/__init__.py
application/data/components/component.json
application/data/current/__init__.py
application/data/current/current.json